Auptimizer-2.0.data/scripts/profiler.sh
Auptimizer-2.0.data/scripts/statscript.sh
aup/__init__.py
aup/__main__.py
aup/aup.py
aup/convert.py
aup/init.py
aup/setup.py
aup/utils.py
aup/visualize.py
aup/EE/Experiment.py
aup/EE/Job.py
aup/EE/__init__.py
aup/EE/Resource/AWSResourceManager.py
aup/EE/Resource/AbstractResourceManager.py
aup/EE/Resource/CPUResourceManager.py
aup/EE/Resource/GPUResourceManager.py
aup/EE/Resource/PassiveResourceManager.py
aup/EE/Resource/SSHResourceManager.py
aup/EE/Resource/__init__.py
aup/EE/Resource/utils/ResourceThreadPoolExecutor.py
aup/EE/Resource/utils/__init__.py
aup/EE/Resource/utils/curve_fitting.py
aup/ET/__init__.py
aup/ET/Connector/AbstractConnector.py
aup/ET/Connector/SQLiteConnector.py
aup/ET/Connector/__init__.py
aup/Proposer/AbstractProposer.py
aup/Proposer/BOHBProposer.py
aup/Proposer/EASProposer.py
aup/Proposer/HyperbandProposer.py
aup/Proposer/HyperoptProposer.py
aup/Proposer/RandomProposer.py
aup/Proposer/SequenceProposer.py
aup/Proposer/SpearmintProposer.py
aup/Proposer/__init__.py
aup/Proposer/eas/__init__.py
aup/Proposer/eas/arch_search.py
aup/Proposer/eas/client.py
aup/Proposer/eas/main.py
aup/Proposer/eas/run_dense_net.py
aup/Proposer/eas/run_simple_convnet.py
aup/Proposer/eas/arch_search/__init__.py
aup/Proposer/eas/arch_search/arch_search_convnet_net2net.py
aup/Proposer/eas/arch_search/arch_search_densenet_net2net.py
aup/Proposer/eas/data_providers/__init__.py
aup/Proposer/eas/data_providers/base_provider.py
aup/Proposer/eas/data_providers/cifar.py
aup/Proposer/eas/data_providers/downloader.py
aup/Proposer/eas/data_providers/svhn.py
aup/Proposer/eas/data_providers/utils.py
aup/Proposer/eas/expdir_monitor/__init__.py
aup/Proposer/eas/expdir_monitor/arch_manager.py
aup/Proposer/eas/expdir_monitor/distributed.py
aup/Proposer/eas/expdir_monitor/expdir_monitor.py
aup/Proposer/eas/meta_controller/__init__.py
aup/Proposer/eas/meta_controller/base_controller.py
aup/Proposer/eas/meta_controller/rl_controller.py
Auptimizer-2.0.dist-info/LICENSE
Auptimizer-2.0.dist-info/METADATA
Auptimizer-2.0.dist-info/WHEEL
Auptimizer-2.0.dist-info/entry_points.txt
Auptimizer-2.0.dist-info/top_level.txt
Auptimizer-2.0.dist-info/RECORD
