Metadata-Version: 2.1
Name: Auptimizer
Version: 2.0
Summary: UNKNOWN
Home-page: https://github.com/LGE-ARC-AdvancedAI/auptimizer
Author: LG Electronics Inc.
Author-email: auptimizer@lge.com
License: SPDX-License-Identifier: GPL-3.0-or-later
Project-URL: Bug Tracker, https://github.com/LGE-ARC-AdvancedAI/auptimizer/issues
Project-URL: Documentation, https://lge-arc-advancedai.github.io/auptimizer/
Project-URL: Source Code, https://github.com/LGE-ARC-AdvancedAI/auptimizer
Platform: UNKNOWN
